{
  "name": "Telco-Customer-Churn",
  "schemaItems": [
    {
      "name": "tenure",
      "valueTypeId": "Number",
      "typeId": "Feature"
    },
    {
      "name": "SeniorCitizen",
      "valueTypeId": "Number",
      "typeId": "Feature"
    },
    {
      "name": "TotalCharges",
      "valueTypeId": "Number",
      "typeId": "Feature"
    },
    {
      "name": "MonthlyCharges",
      "valueTypeId": "Number",
      "typeId": "Feature"
    },
    {
      "name": "customerID",
      "valueTypeId": "String",
      "typeId": "Info"
    },
    {
      "name": "gender",
      "valueTypeId": "Category",
      "typeId": "Feature",
      "categories": [
        {
          "value": "male"
        },
        {
          "value": "female"
        }
      ]
    },
    {
      "name": "MultipleLines",
      "valueTypeId": "Category",
      "typeId": "Feature",
      "categories": [
        {
          "value": "no"
        },
        {
          "value": "no phone service"
        },
        {
          "value": "yes"
        }
      ]
    },
    {
      "name": "PhoneService",
      "valueTypeId": "Category",
      "typeId": "Feature",
      "categories": [
        {
          "value": "yes"
        },
        {
          "value": "no"
        }
      ]
    },
    {
      "name": "Partner",
      "valueTypeId": "Category",
      "typeId": "Feature",
      "categories": [
        {
          "value": "yes"
        },
        {
          "value": "no"
        }
      ]
    },
    {
      "name": "Dependents",
      "valueTypeId": "Category",
      "typeId": "Feature",
      "categories": [
        {
          "value": "no"
        },
        {
          "value": "yes"
        }
      ]
    },
    {
      "name": "OnlineSecurity",
      "valueTypeId": "Category",
      "typeId": "Feature",
      "categories": [
        {
          "value": "no internet service"
        },
        {
          "value": "no"
        },
        {
          "value": "yes"
        }
      ]
    },
    {
      "name": "TechSupport",
      "valueTypeId": "Category",
      "typeId": "Feature",
      "categories": [
        {
          "value": "yes"
        },
        {
          "value": "no"
        },
        {
          "value": "no internet service"
        }
      ]
    },
    {
      "name": "StreamingTV",
      "valueTypeId": "Category",
      "typeId": "Feature",
      "categories": [
        {
          "value": "yes"
        },
        {
          "value": "no"
        },
        {
          "value": "no internet service"
        }
      ]
    },
    {
      "name": "OnlineBackup",
      "valueTypeId": "Category",
      "typeId": "Feature",
      "categories": [
        {
          "value": "no"
        },
        {
          "value": "no internet service"
        },
        {
          "value": "yes"
        }
      ]
    },
    {
      "name": "StreamingMovies",
      "valueTypeId": "Category",
      "typeId": "Feature",
      "categories": [
        {
          "value": "yes"
        },
        {
          "value": "no"
        },
        {
          "value": "no internet service"
        }
      ]
    },
    {
      "name": "PaperlessBilling",
      "valueTypeId": "Category",
      "typeId": "Feature",
      "categories": [
        {
          "value": "yes"
        },
        {
          "value": "no"
        }
      ]
    },
    {
      "name": "DeviceProtection",
      "valueTypeId": "Category",
      "typeId": "Feature",
      "categories": [
        {
          "value": "no internet service"
        },
        {
          "value": "no"
        },
        {
          "value": "yes"
        }
      ]
    },
    {
      "name": "InternetService",
      "valueTypeId": "Category",
      "typeId": "Feature",
      "categories": [
        {
          "value": "dsl"
        },
        {
          "value": "fiber optic"
        },
        {
          "value": "no"
        }
      ]
    },
    {
      "name": "PaymentMethod",
      "valueTypeId": "Category",
      "typeId": "Feature",
      "categories": [
        {
          "value": "electronic check"
        },
        {
          "value": "bank transfer (automatic)"
        },
        {
          "value": "mailed check"
        },
        {
          "value": "credit card (automatic)"
        }
      ]
    },
    {
      "name": "Churn",
      "valueTypeId": "Category",
      "typeId": "Target",
      "categories": [
        {
          "value": "yes"
        },
        {
          "value": "no"
        }
      ]
    },
    {
      "name": "Contract",
      "valueTypeId": "Category",
      "typeId": "Feature",
      "categories": [
        {
          "value": "month-to-month"
        },
        {
          "value": "two year"
        },
        {
          "value": "one year"
        }
      ]
    }
  ],
  "description": ""
}